{
    "convn_valid": {
        "return_type": "void",
        "para": [
            [
                "double[1024]",
                "in_data"
            ],
            [
                "int",
                "in_w"
            ],
            [
                "int",
                "in_h"
            ],
            [
                "double[25]",
                "kernel"
            ],
            [
                "int",
                "kernel_w"
            ],
            [
                "int",
                "kernel_h"
            ],
            [
                "double[1024]",
                "out_data"
            ],
            [
                "int",
                "out_w"
            ],
            [
                "int",
                "out_h"
            ]
        ],
        "func_impl": "void convn_valid(double in_data[MAX_MAP_SIZE], int in_w, int in_h, double kernel[MAX_KERNEL_SIZE], int kernel_w, int kernel_h, double out_data[MAX_MAP_SIZE], int out_w, int out_h) ",
        "is_impl_func": false,
        "visible": false
    },
    "conv_fprop1": {
        "return_type": "void",
        "para": [
            [
                "Layer *",
                "input_layer"
            ],
            [
                "Layer *",
                "c1_conv_layer"
            ],
            [
                "bool[96]",
                "pconnection"
            ]
        ],
        "func_impl": "void IMPL(conv_fprop1)(HLS_COMMON_ARG Layer *input_layer, Layer *c1_conv_layer, bool pconnection[96]) ",
        "is_impl_func": true,
        "visible": true
    },
    "conv_fprop2": {
        "return_type": "void",
        "para": [
            [
                "Layer *",
                "s2_pooling_la"
            ],
            [
                "Layer *",
                "c3_conv_layer"
            ],
            [
                "bool[96]",
                "pconnection"
            ]
        ],
        "func_impl": "void IMPL(conv_fprop2)(HLS_COMMON_ARG Layer *s2_pooling_la, Layer *c3_conv_layer, bool pconnection[96]) ",
        "is_impl_func": true,
        "visible": true
    },
    "conv_fprop3": {
        "return_type": "void",
        "para": [
            [
                "Layer *",
                "s4_pooling_layer"
            ],
            [
                "Layer *",
                "c5_conv_layer"
            ],
            [
                "bool[96]",
                "pconnection"
            ]
        ],
        "func_impl": "void IMPL(conv_fprop3)(HLS_COMMON_ARG Layer *s4_pooling_layer, Layer *c5_conv_layer, bool pconnection[96]) ",
        "is_impl_func": true,
        "visible": true
    },
    "max_pooling_fprop1": {
        "return_type": "void",
        "para": [
            [
                "Layer *",
                "c1_conv_layer"
            ],
            [
                "Layer *",
                "s2_pooling_layer"
            ]
        ],
        "func_impl": "void IMPL(max_pooling_fprop1)(HLS_COMMON_ARG Layer *c1_conv_layer, Layer *s2_pooling_layer) ",
        "is_impl_func": true,
        "visible": true
    },
    "max_pooling_fprop2": {
        "return_type": "void",
        "para": [
            [
                "Layer *",
                "c3_conv_layer"
            ],
            [
                "Layer *",
                "s4_pooling_layer"
            ]
        ],
        "func_impl": "void IMPL(max_pooling_fprop2)(HLS_COMMON_ARG Layer *c3_conv_layer, Layer *s4_pooling_layer) ",
        "is_impl_func": true,
        "visible": true
    },
    "fully_connected_fprop": {
        "return_type": "void",
        "para": [
            [
                "Layer *",
                "c5_conv_layer"
            ],
            [
                "Layer *",
                "output_layer"
            ]
        ],
        "func_impl": "void IMPL(fully_connected_fprop)(HLS_COMMON_ARG Layer *c5_conv_layer, Layer *output_layer) ",
        "is_impl_func": true,
        "visible": true
    }
}