<?xml version="1.0" encoding="utf-8"?>
<BindInfo>
	<BindNode BINDTYPE="op" DISPLAY="bind_op add" ID="" IMPL="fabric" LATENCY="0" OPTYPE="add" PRAGMA="" RTLNAME="empty_16_fu_69_p2" SOURCE="" VARIABLE="empty_16" MODULE="conv_fprop1_Pipeline_1" LOOP="Loop 1" BUNDLEDNAME="" DSP="0" BRAM="0" URAM="0" USAGE="" STORAGESUBTYPE="" STORAGESIZE=""/>
	<BindNode BINDTYPE="op" DISPLAY="bind_op seteq" ID="" IMPL="auto" LATENCY="0" OPTYPE="seteq" PRAGMA="" RTLNAME="exitcond_fu_79_p2" SOURCE="" VARIABLE="exitcond" MODULE="conv_fprop1_Pipeline_1" LOOP="Loop 1" BUNDLEDNAME="" DSP="0" BRAM="0" URAM="0" USAGE="" STORAGESUBTYPE="" STORAGESIZE=""/>
	<BindNode BINDTYPE="op" DISPLAY="bind_op setlt" ID="" IMPL="auto" LATENCY="0" OPTYPE="setlt" PRAGMA="" RTLNAME="icmp_ln86_fu_194_p2" SOURCE="../source/hls.cpp:86" VARIABLE="icmp_ln86" MODULE="conv_fprop1_Pipeline_VITIS_LOOP_84_3_VITIS_LOOP_86_4" LOOP="VITIS_LOOP_84_3_VITIS_LOOP_86_4" BUNDLEDNAME="" DSP="0" BRAM="0" URAM="0" USAGE="" STORAGESUBTYPE="" STORAGESIZE=""/>
	<BindNode BINDTYPE="op" DISPLAY="bind_op seteq" ID="" IMPL="auto" LATENCY="0" OPTYPE="seteq" PRAGMA="" RTLNAME="icmp_ln84_fu_199_p2" SOURCE="../source/hls.cpp:84" VARIABLE="icmp_ln84" MODULE="conv_fprop1_Pipeline_VITIS_LOOP_84_3_VITIS_LOOP_86_4" LOOP="VITIS_LOOP_84_3_VITIS_LOOP_86_4" BUNDLEDNAME="" DSP="0" BRAM="0" URAM="0" USAGE="" STORAGESUBTYPE="" STORAGESIZE=""/>
	<BindNode BINDTYPE="op" DISPLAY="bind_op add" ID="" IMPL="fabric" LATENCY="0" OPTYPE="add" PRAGMA="" RTLNAME="add_ln84_1_fu_204_p2" SOURCE="../source/hls.cpp:84" VARIABLE="add_ln84_1" MODULE="conv_fprop1_Pipeline_VITIS_LOOP_84_3_VITIS_LOOP_86_4" LOOP="VITIS_LOOP_84_3_VITIS_LOOP_86_4" BUNDLEDNAME="" DSP="0" BRAM="0" URAM="0" USAGE="" STORAGESUBTYPE="" STORAGESIZE=""/>
	<BindNode BINDTYPE="op" DISPLAY="bind_op add" ID="" IMPL="fabric" LATENCY="0" OPTYPE="add" PRAGMA="" RTLNAME="add_ln84_fu_213_p2" SOURCE="../source/hls.cpp:84" VARIABLE="add_ln84" MODULE="conv_fprop1_Pipeline_VITIS_LOOP_84_3_VITIS_LOOP_86_4" LOOP="VITIS_LOOP_84_3_VITIS_LOOP_86_4" BUNDLEDNAME="" DSP="0" BRAM="0" URAM="0" USAGE="" STORAGESUBTYPE="" STORAGESIZE=""/>
	<BindNode BINDTYPE="op" DISPLAY="bind_op select" ID="" IMPL="auto_sel" LATENCY="0" OPTYPE="select" PRAGMA="" RTLNAME="select_ln84_fu_245_p3" SOURCE="../source/hls.cpp:84" VARIABLE="select_ln84" MODULE="conv_fprop1_Pipeline_VITIS_LOOP_84_3_VITIS_LOOP_86_4" LOOP="VITIS_LOOP_84_3_VITIS_LOOP_86_4" BUNDLEDNAME="" DSP="0" BRAM="0" URAM="0" USAGE="" STORAGESUBTYPE="" STORAGESIZE=""/>
	<BindNode BINDTYPE="op" DISPLAY="bind_op select" ID="" IMPL="auto_sel" LATENCY="0" OPTYPE="select" PRAGMA="" RTLNAME="select_ln84_1_fu_219_p3" SOURCE="../source/hls.cpp:84" VARIABLE="select_ln84_1" MODULE="conv_fprop1_Pipeline_VITIS_LOOP_84_3_VITIS_LOOP_86_4" LOOP="VITIS_LOOP_84_3_VITIS_LOOP_86_4" BUNDLEDNAME="" DSP="0" BRAM="0" URAM="0" USAGE="" STORAGESUBTYPE="" STORAGESIZE=""/>
	<BindNode BINDTYPE="op" DISPLAY="bind_op add" ID="" IMPL="dsp_slice" LATENCY="3" OPTYPE="add" PRAGMA="" RTLNAME="ama_addmuladd_17ns_17ns_17s_17ns_17_4_1_U6" SOURCE="../source/hls.cpp:84" VARIABLE="empty_13" MODULE="conv_fprop1_Pipeline_VITIS_LOOP_84_3_VITIS_LOOP_86_4" LOOP="VITIS_LOOP_84_3_VITIS_LOOP_86_4" BUNDLEDNAME="" DSP="1" BRAM="0" URAM="0" USAGE="" STORAGESUBTYPE="" STORAGESIZE=""/>
	<BindNode BINDTYPE="op" DISPLAY="bind_op mul" ID="" IMPL="dsp_slice" LATENCY="3" OPTYPE="mul" PRAGMA="" RTLNAME="ama_addmuladd_17ns_17ns_17s_17ns_17_4_1_U6" SOURCE="../source/hls.cpp:84" VARIABLE="empty_14" MODULE="conv_fprop1_Pipeline_VITIS_LOOP_84_3_VITIS_LOOP_86_4" LOOP="VITIS_LOOP_84_3_VITIS_LOOP_86_4" BUNDLEDNAME="" DSP="1" BRAM="0" URAM="0" USAGE="" STORAGESUBTYPE="" STORAGESIZE=""/>
	<BindNode BINDTYPE="op" DISPLAY="bind_op mul" ID="" IMPL="auto" LATENCY="1" OPTYPE="mul" PRAGMA="" RTLNAME="mul_31ns_32s_58_2_1_U5" SOURCE="../source/hls.cpp:84" VARIABLE="empty_15" MODULE="conv_fprop1_Pipeline_VITIS_LOOP_84_3_VITIS_LOOP_86_4" LOOP="VITIS_LOOP_84_3_VITIS_LOOP_86_4" BUNDLEDNAME="" DSP="4" BRAM="0" URAM="0" USAGE="" STORAGESUBTYPE="" STORAGESIZE=""/>
	<BindNode BINDTYPE="op" DISPLAY="bind_op add" ID="" IMPL="fabric" LATENCY="0" OPTYPE="add" PRAGMA="" RTLNAME="grp_fu_329_p3" SOURCE="../source/hls.cpp:88" VARIABLE="add_ln88_1" MODULE="conv_fprop1_Pipeline_VITIS_LOOP_84_3_VITIS_LOOP_86_4" LOOP="VITIS_LOOP_84_3_VITIS_LOOP_86_4" BUNDLEDNAME="" DSP="0" BRAM="0" URAM="0" USAGE="" STORAGESUBTYPE="" STORAGESIZE=""/>
	<BindNode BINDTYPE="op" DISPLAY="bind_op add" ID="" IMPL="dsp_slice" LATENCY="3" OPTYPE="add" PRAGMA="" RTLNAME="ama_addmuladd_17ns_17ns_17s_17ns_17_4_1_U6" SOURCE="../source/hls.cpp:88" VARIABLE="add_ln88" MODULE="conv_fprop1_Pipeline_VITIS_LOOP_84_3_VITIS_LOOP_86_4" LOOP="VITIS_LOOP_84_3_VITIS_LOOP_86_4" BUNDLEDNAME="" DSP="1" BRAM="0" URAM="0" USAGE="" STORAGESUBTYPE="" STORAGESIZE=""/>
	<BindNode BINDTYPE="op" DISPLAY="bind_op add" ID="" IMPL="fabric" LATENCY="0" OPTYPE="add" PRAGMA="" RTLNAME="add_ln88_3_fu_280_p2" SOURCE="../source/hls.cpp:88" VARIABLE="add_ln88_3" MODULE="conv_fprop1_Pipeline_VITIS_LOOP_84_3_VITIS_LOOP_86_4" LOOP="VITIS_LOOP_84_3_VITIS_LOOP_86_4" BUNDLEDNAME="" DSP="0" BRAM="0" URAM="0" USAGE="" STORAGESUBTYPE="" STORAGESIZE=""/>
	<BindNode BINDTYPE="op" DISPLAY="bind_op add" ID="" IMPL="fabric" LATENCY="0" OPTYPE="add" PRAGMA="" RTLNAME="add_ln88_2_fu_264_p2" SOURCE="../source/hls.cpp:88" VARIABLE="add_ln88_2" MODULE="conv_fprop1_Pipeline_VITIS_LOOP_84_3_VITIS_LOOP_86_4" LOOP="VITIS_LOOP_84_3_VITIS_LOOP_86_4" BUNDLEDNAME="" DSP="0" BRAM="0" URAM="0" USAGE="" STORAGESUBTYPE="" STORAGESIZE=""/>
	<BindNode BINDTYPE="op" DISPLAY="bind_op lshr" ID="" IMPL="auto_pipe" LATENCY="0" OPTYPE="lshr" PRAGMA="" RTLNAME="lshr_ln88_fu_295_p2" SOURCE="../source/hls.cpp:88" VARIABLE="lshr_ln88" MODULE="conv_fprop1_Pipeline_VITIS_LOOP_84_3_VITIS_LOOP_86_4" LOOP="VITIS_LOOP_84_3_VITIS_LOOP_86_4" BUNDLEDNAME="" DSP="0" BRAM="0" URAM="0" USAGE="" STORAGESUBTYPE="" STORAGESIZE=""/>
	<BindNode BINDTYPE="op" DISPLAY="bind_op dmul" ID="" IMPL="maxdsp" LATENCY="7" OPTYPE="dmul" PRAGMA="" RTLNAME="dmul_64ns_64ns_64_8_max_dsp_1_U4" SOURCE="../source/hls.cpp:88" VARIABLE="mul19_i" MODULE="conv_fprop1_Pipeline_VITIS_LOOP_84_3_VITIS_LOOP_86_4" LOOP="VITIS_LOOP_84_3_VITIS_LOOP_86_4" BUNDLEDNAME="" DSP="8" BRAM="0" URAM="0" USAGE="" STORAGESUBTYPE="" STORAGESIZE=""/>
	<BindNode BINDTYPE="op" DISPLAY="bind_op add" ID="" IMPL="fabric" LATENCY="0" OPTYPE="add" PRAGMA="" RTLNAME="add_ln86_fu_269_p2" SOURCE="../source/hls.cpp:86" VARIABLE="add_ln86" MODULE="conv_fprop1_Pipeline_VITIS_LOOP_84_3_VITIS_LOOP_86_4" LOOP="VITIS_LOOP_84_3_VITIS_LOOP_86_4" BUNDLEDNAME="" DSP="0" BRAM="0" URAM="0" USAGE="" STORAGESUBTYPE="" STORAGESIZE=""/>
	<BindNode BINDTYPE="op" DISPLAY="bind_op setlt" ID="" IMPL="auto" LATENCY="0" OPTYPE="setlt" PRAGMA="" RTLNAME="icmp_ln132_fu_136_p2" SOURCE="../source/hls.cpp:132" VARIABLE="icmp_ln132" MODULE="conv_fprop1_Pipeline_VITIS_LOOP_132_3" LOOP="VITIS_LOOP_132_3" BUNDLEDNAME="" DSP="0" BRAM="0" URAM="0" USAGE="" STORAGESUBTYPE="" STORAGESIZE=""/>
	<BindNode BINDTYPE="op" DISPLAY="bind_op add" ID="" IMPL="fabric" LATENCY="0" OPTYPE="add" PRAGMA="" RTLNAME="add_ln132_fu_142_p2" SOURCE="../source/hls.cpp:132" VARIABLE="add_ln132" MODULE="conv_fprop1_Pipeline_VITIS_LOOP_132_3" LOOP="VITIS_LOOP_132_3" BUNDLEDNAME="" DSP="0" BRAM="0" URAM="0" USAGE="" STORAGESUBTYPE="" STORAGESIZE=""/>
	<BindNode BINDTYPE="op" DISPLAY="bind_op add" ID="" IMPL="fabric" LATENCY="0" OPTYPE="add" PRAGMA="" RTLNAME="add_ln134_fu_153_p2" SOURCE="../source/hls.cpp:134" VARIABLE="add_ln134" MODULE="conv_fprop1_Pipeline_VITIS_LOOP_132_3" LOOP="VITIS_LOOP_132_3" BUNDLEDNAME="" DSP="0" BRAM="0" URAM="0" USAGE="" STORAGESUBTYPE="" STORAGESIZE=""/>
	<BindNode BINDTYPE="op" DISPLAY="bind_op dadd" ID="" IMPL="fulldsp" LATENCY="7" OPTYPE="dadd" PRAGMA="" RTLNAME="dadd_64ns_64ns_64_8_full_dsp_1_U20" SOURCE="../source/hls.cpp:134" VARIABLE="val_assign" MODULE="conv_fprop1_Pipeline_VITIS_LOOP_132_3" LOOP="VITIS_LOOP_132_3" BUNDLEDNAME="" DSP="3" BRAM="0" URAM="0" USAGE="" STORAGESUBTYPE="" STORAGESIZE=""/>
	<BindNode BINDTYPE="op" DISPLAY="bind_op dexp" ID="" IMPL="fulldsp" LATENCY="29" OPTYPE="dexp" PRAGMA="" RTLNAME="dexp_64ns_64ns_64_30_full_dsp_1_U24" SOURCE="../source/hls.cpp:10" VARIABLE="ep" MODULE="conv_fprop1_Pipeline_VITIS_LOOP_132_3" LOOP="VITIS_LOOP_132_3" BUNDLEDNAME="" DSP="26" BRAM="0" URAM="0" USAGE="" STORAGESUBTYPE="" STORAGESIZE=""/>
	<BindNode BINDTYPE="op" DISPLAY="bind_op xor" ID="" IMPL="auto" LATENCY="0" OPTYPE="xor" PRAGMA="" RTLNAME="xor_ln11_fu_179_p2" SOURCE="../source/hls.cpp:11" VARIABLE="xor_ln11" MODULE="conv_fprop1_Pipeline_VITIS_LOOP_132_3" LOOP="VITIS_LOOP_132_3" BUNDLEDNAME="" DSP="0" BRAM="0" URAM="0" USAGE="" STORAGESUBTYPE="" STORAGESIZE=""/>
	<BindNode BINDTYPE="op" DISPLAY="bind_op dexp" ID="" IMPL="fulldsp" LATENCY="29" OPTYPE="dexp" PRAGMA="" RTLNAME="dexp_64ns_64ns_64_30_full_dsp_1_U25" SOURCE="../source/hls.cpp:11" VARIABLE="em" MODULE="conv_fprop1_Pipeline_VITIS_LOOP_132_3" LOOP="VITIS_LOOP_132_3" BUNDLEDNAME="" DSP="26" BRAM="0" URAM="0" USAGE="" STORAGESUBTYPE="" STORAGESIZE=""/>
	<BindNode BINDTYPE="op" DISPLAY="bind_op dadd" ID="" IMPL="fulldsp" LATENCY="7" OPTYPE="dadd" PRAGMA="" RTLNAME="dadd_64ns_64ns_64_8_full_dsp_1_U22" SOURCE="../source/hls.cpp:13" VARIABLE="add_i" MODULE="conv_fprop1_Pipeline_VITIS_LOOP_132_3" LOOP="VITIS_LOOP_132_3" BUNDLEDNAME="" DSP="3" BRAM="0" URAM="0" USAGE="" STORAGESUBTYPE="" STORAGESIZE=""/>
	<BindNode BINDTYPE="op" DISPLAY="bind_op ddiv" ID="" IMPL="fabric" LATENCY="30" OPTYPE="ddiv" PRAGMA="" RTLNAME="ddiv_64ns_64ns_64_31_no_dsp_1_U23" SOURCE="../source/hls.cpp:13" VARIABLE="div_i" MODULE="conv_fprop1_Pipeline_VITIS_LOOP_132_3" LOOP="VITIS_LOOP_132_3" BUNDLEDNAME="" DSP="0" BRAM="0" URAM="0" USAGE="" STORAGESUBTYPE="" STORAGESIZE=""/>
	<BindNode BINDTYPE="op" DISPLAY="bind_op mul" ID="" IMPL="auto" LATENCY="1" OPTYPE="mul" PRAGMA="" RTLNAME="mul_32s_32s_32_2_1_U36" SOURCE="../source/hls.cpp:114" VARIABLE="size" MODULE="conv_fprop1" LOOP="" BUNDLEDNAME="" DSP="3" BRAM="0" URAM="0" USAGE="" STORAGESUBTYPE="" STORAGESIZE=""/>
	<BindNode BINDTYPE="op" DISPLAY="bind_op seteq" ID="" IMPL="auto" LATENCY="0" OPTYPE="seteq" PRAGMA="" RTLNAME="empty_fu_297_p2" SOURCE="../source/hls.cpp:114" VARIABLE="empty" MODULE="conv_fprop1" LOOP="" BUNDLEDNAME="" DSP="0" BRAM="0" URAM="0" USAGE="" STORAGESUBTYPE="" STORAGESIZE=""/>
	<BindNode BINDTYPE="op" DISPLAY="bind_op setlt" ID="" IMPL="auto" LATENCY="0" OPTYPE="setlt" PRAGMA="" RTLNAME="icmp_ln115_fu_313_p2" SOURCE="../source/hls.cpp:115" VARIABLE="icmp_ln115" MODULE="conv_fprop1" LOOP="VITIS_LOOP_115_1" BUNDLEDNAME="" DSP="0" BRAM="0" URAM="0" USAGE="" STORAGESUBTYPE="" STORAGESIZE=""/>
	<BindNode BINDTYPE="op" DISPLAY="bind_op add" ID="" IMPL="fabric" LATENCY="0" OPTYPE="add" PRAGMA="" RTLNAME="add_ln115_fu_318_p2" SOURCE="../source/hls.cpp:115" VARIABLE="add_ln115" MODULE="conv_fprop1" LOOP="VITIS_LOOP_115_1" BUNDLEDNAME="" DSP="0" BRAM="0" URAM="0" USAGE="" STORAGESUBTYPE="" STORAGESIZE=""/>
	<BindNode BINDTYPE="op" DISPLAY="bind_op setgt" ID="" IMPL="auto" LATENCY="0" OPTYPE="setgt" PRAGMA="" RTLNAME="empty_19_fu_352_p2" SOURCE="../source/hls.cpp:128" VARIABLE="empty_19" MODULE="conv_fprop1" LOOP="VITIS_LOOP_115_1" BUNDLEDNAME="" DSP="0" BRAM="0" URAM="0" USAGE="" STORAGESUBTYPE="" STORAGESIZE=""/>
	<BindNode BINDTYPE="op" DISPLAY="bind_op select" ID="" IMPL="auto_sel" LATENCY="0" OPTYPE="select" PRAGMA="" RTLNAME="smax_fu_358_p3" SOURCE="../source/hls.cpp:128" VARIABLE="smax" MODULE="conv_fprop1" LOOP="VITIS_LOOP_115_1" BUNDLEDNAME="" DSP="0" BRAM="0" URAM="0" USAGE="" STORAGESUBTYPE="" STORAGESIZE=""/>
	<BindNode BINDTYPE="op" DISPLAY="bind_op setgt" ID="" IMPL="auto" LATENCY="0" OPTYPE="setgt" PRAGMA="" RTLNAME="empty_20_fu_366_p2" SOURCE="../source/hls.cpp:128" VARIABLE="empty_20" MODULE="conv_fprop1" LOOP="VITIS_LOOP_115_1" BUNDLEDNAME="" DSP="0" BRAM="0" URAM="0" USAGE="" STORAGESUBTYPE="" STORAGESIZE=""/>
	<BindNode BINDTYPE="op" DISPLAY="bind_op select" ID="" IMPL="auto_sel" LATENCY="0" OPTYPE="select" PRAGMA="" RTLNAME="smax1_fu_372_p3" SOURCE="../source/hls.cpp:128" VARIABLE="smax1" MODULE="conv_fprop1" LOOP="VITIS_LOOP_115_1" BUNDLEDNAME="" DSP="0" BRAM="0" URAM="0" USAGE="" STORAGESUBTYPE="" STORAGESIZE=""/>
	<BindNode BINDTYPE="op" DISPLAY="bind_op mul" ID="" IMPL="auto" LATENCY="1" OPTYPE="mul" PRAGMA="" RTLNAME="mul_31ns_31ns_62_2_1_U35" SOURCE="../source/hls.cpp:127" VARIABLE="mul_ln127" MODULE="conv_fprop1" LOOP="VITIS_LOOP_115_1" BUNDLEDNAME="" DSP="4" BRAM="0" URAM="0" USAGE="" STORAGESUBTYPE="" STORAGESIZE=""/>
	<BindNode BINDTYPE="op" DISPLAY="bind_op setlt" ID="" IMPL="auto" LATENCY="0" OPTYPE="setlt" PRAGMA="" RTLNAME="icmp_ln118_fu_396_p2" SOURCE="../source/hls.cpp:118" VARIABLE="icmp_ln118" MODULE="conv_fprop1" LOOP="VITIS_LOOP_118_2" BUNDLEDNAME="" DSP="0" BRAM="0" URAM="0" USAGE="" STORAGESUBTYPE="" STORAGESIZE=""/>
	<BindNode BINDTYPE="op" DISPLAY="bind_op add" ID="" IMPL="fabric" LATENCY="0" OPTYPE="add" PRAGMA="" RTLNAME="add_ln118_fu_401_p2" SOURCE="../source/hls.cpp:118" VARIABLE="add_ln118" MODULE="conv_fprop1" LOOP="VITIS_LOOP_118_2" BUNDLEDNAME="" DSP="0" BRAM="0" URAM="0" USAGE="" STORAGESUBTYPE="" STORAGESIZE=""/>
	<BindNode BINDTYPE="op" DISPLAY="bind_op mul" ID="" IMPL="dsp_slice" LATENCY="3" OPTYPE="mul" PRAGMA="" RTLNAME="mac_muladd_11s_11s_11ns_11_4_1_U38" SOURCE="../source/hls.cpp:120" VARIABLE="mul_ln120" MODULE="conv_fprop1" LOOP="VITIS_LOOP_118_2" BUNDLEDNAME="" DSP="1" BRAM="0" URAM="0" USAGE="" STORAGESUBTYPE="" STORAGESIZE=""/>
	<BindNode BINDTYPE="op" DISPLAY="bind_op add" ID="" IMPL="dsp_slice" LATENCY="3" OPTYPE="add" PRAGMA="" RTLNAME="mac_muladd_11s_11s_11ns_11_4_1_U38" SOURCE="../source/hls.cpp:120" VARIABLE="add_ln120" MODULE="conv_fprop1" LOOP="VITIS_LOOP_118_2" BUNDLEDNAME="" DSP="1" BRAM="0" URAM="0" USAGE="" STORAGESUBTYPE="" STORAGESIZE=""/>
	<BindNode BINDTYPE="op" DISPLAY="bind_op setlt" ID="" IMPL="auto" LATENCY="0" OPTYPE="setlt" PRAGMA="" RTLNAME="icmp_ln79_fu_434_p2" SOURCE="../source/hls.cpp:79" VARIABLE="icmp_ln79" MODULE="conv_fprop1" LOOP="VITIS_LOOP_79_1" BUNDLEDNAME="" DSP="0" BRAM="0" URAM="0" USAGE="" STORAGESUBTYPE="" STORAGESIZE=""/>
	<BindNode BINDTYPE="op" DISPLAY="bind_op add" ID="" IMPL="fabric" LATENCY="0" OPTYPE="add" PRAGMA="" RTLNAME="add_ln79_fu_439_p2" SOURCE="../source/hls.cpp:79" VARIABLE="add_ln79" MODULE="conv_fprop1" LOOP="VITIS_LOOP_79_1" BUNDLEDNAME="" DSP="0" BRAM="0" URAM="0" USAGE="" STORAGESUBTYPE="" STORAGESIZE=""/>
	<BindNode BINDTYPE="op" DISPLAY="bind_op mul" ID="" IMPL="auto" LATENCY="0" OPTYPE="mul" PRAGMA="" RTLNAME="mul_10s_10s_10_1_1_U37" SOURCE="../source/hls.cpp:79" VARIABLE="empty_21" MODULE="conv_fprop1" LOOP="VITIS_LOOP_79_1" BUNDLEDNAME="" DSP="0" BRAM="0" URAM="0" USAGE="" STORAGESUBTYPE="" STORAGESIZE=""/>
	<BindNode BINDTYPE="op" DISPLAY="bind_op setlt" ID="" IMPL="auto" LATENCY="0" OPTYPE="setlt" PRAGMA="" RTLNAME="icmp_ln81_fu_462_p2" SOURCE="../source/hls.cpp:81" VARIABLE="icmp_ln81" MODULE="conv_fprop1" LOOP="VITIS_LOOP_81_2" BUNDLEDNAME="" DSP="0" BRAM="0" URAM="0" USAGE="" STORAGESUBTYPE="" STORAGESIZE=""/>
	<BindNode BINDTYPE="op" DISPLAY="bind_op add" ID="" IMPL="fabric" LATENCY="0" OPTYPE="add" PRAGMA="" RTLNAME="add_ln81_fu_467_p2" SOURCE="../source/hls.cpp:81" VARIABLE="add_ln81" MODULE="conv_fprop1" LOOP="VITIS_LOOP_81_2" BUNDLEDNAME="" DSP="0" BRAM="0" URAM="0" USAGE="" STORAGESUBTYPE="" STORAGESIZE=""/>
	<BindNode BINDTYPE="op" DISPLAY="bind_op add" ID="" IMPL="fabric" LATENCY="0" OPTYPE="add" PRAGMA="" RTLNAME="add_ln91_fu_482_p2" SOURCE="../source/hls.cpp:91" VARIABLE="add_ln91" MODULE="conv_fprop1" LOOP="VITIS_LOOP_81_2" BUNDLEDNAME="" DSP="0" BRAM="0" URAM="0" USAGE="" STORAGESUBTYPE="" STORAGESIZE=""/>
	<BindNode BINDTYPE="op" DISPLAY="bind_op dadd" ID="" IMPL="fulldsp" LATENCY="7" OPTYPE="dadd" PRAGMA="" RTLNAME="dadddsub_64ns_64ns_64_8_full_dsp_1_U34" SOURCE="../source/hls.cpp:91" VARIABLE="add28_i" MODULE="conv_fprop1" LOOP="VITIS_LOOP_81_2" BUNDLEDNAME="" DSP="3" BRAM="0" URAM="0" USAGE="" STORAGESUBTYPE="" STORAGESIZE=""/>
	<BindNode BINDTYPE="interface" DISPLAY="bind_storage bram" ID="" IMPL="" LATENCY="" OPTYPE="" PRAGMA="no" RTLNAME="" SOURCE="" VARIABLE="input_layer_map_data" MODULE="conv_fprop1" LOOP="" BUNDLEDNAME="" DSP="0" BRAM="0" URAM="0" USAGE="interface" STORAGESUBTYPE="bram" STORAGESIZE="64 0 1"/>
	<BindNode BINDTYPE="interface" DISPLAY="bind_storage bram" ID="" IMPL="" LATENCY="" OPTYPE="" PRAGMA="no" RTLNAME="" SOURCE="" VARIABLE="input_layer_map_error" MODULE="conv_fprop1" LOOP="" BUNDLEDNAME="" DSP="0" BRAM="0" URAM="0" USAGE="interface" STORAGESUBTYPE="bram" STORAGESIZE="64 0 1"/>
	<BindNode BINDTYPE="interface" DISPLAY="bind_storage bram" ID="" IMPL="" LATENCY="" OPTYPE="" PRAGMA="no" RTLNAME="" SOURCE="" VARIABLE="input_layer_map_b" MODULE="conv_fprop1" LOOP="" BUNDLEDNAME="" DSP="0" BRAM="0" URAM="0" USAGE="interface" STORAGESUBTYPE="bram" STORAGESIZE="64 0 1"/>
	<BindNode BINDTYPE="interface" DISPLAY="bind_storage bram" ID="" IMPL="" LATENCY="" OPTYPE="" PRAGMA="no" RTLNAME="" SOURCE="" VARIABLE="input_layer_map_db" MODULE="conv_fprop1" LOOP="" BUNDLEDNAME="" DSP="0" BRAM="0" URAM="0" USAGE="interface" STORAGESUBTYPE="bram" STORAGESIZE="64 0 1"/>
	<BindNode BINDTYPE="interface" DISPLAY="bind_storage bram" ID="" IMPL="" LATENCY="" OPTYPE="" PRAGMA="no" RTLNAME="" SOURCE="" VARIABLE="input_layer_kernel" MODULE="conv_fprop1" LOOP="" BUNDLEDNAME="" DSP="0" BRAM="0" URAM="0" USAGE="interface" STORAGESUBTYPE="bram" STORAGESIZE="3200 0 1"/>
	<BindNode BINDTYPE="interface" DISPLAY="bind_storage bram" ID="" IMPL="" LATENCY="" OPTYPE="" PRAGMA="no" RTLNAME="" SOURCE="" VARIABLE="input_layer_map_common" MODULE="conv_fprop1" LOOP="" BUNDLEDNAME="" DSP="0" BRAM="0" URAM="0" USAGE="interface" STORAGESUBTYPE="bram" STORAGESIZE="64 0 1"/>
	<BindNode BINDTYPE="interface" DISPLAY="bind_storage bram" ID="" IMPL="" LATENCY="" OPTYPE="" PRAGMA="no" RTLNAME="" SOURCE="" VARIABLE="c1_conv_layer_map_data" MODULE="conv_fprop1" LOOP="" BUNDLEDNAME="" DSP="0" BRAM="0" URAM="0" USAGE="interface" STORAGESUBTYPE="bram" STORAGESIZE="64 0 1"/>
	<BindNode BINDTYPE="interface" DISPLAY="bind_storage bram" ID="" IMPL="" LATENCY="" OPTYPE="" PRAGMA="no" RTLNAME="" SOURCE="" VARIABLE="c1_conv_layer_map_error" MODULE="conv_fprop1" LOOP="" BUNDLEDNAME="" DSP="0" BRAM="0" URAM="0" USAGE="interface" STORAGESUBTYPE="bram" STORAGESIZE="64 0 1"/>
	<BindNode BINDTYPE="interface" DISPLAY="bind_storage bram" ID="" IMPL="" LATENCY="" OPTYPE="" PRAGMA="no" RTLNAME="" SOURCE="" VARIABLE="c1_conv_layer_map_b" MODULE="conv_fprop1" LOOP="" BUNDLEDNAME="" DSP="0" BRAM="0" URAM="0" USAGE="interface" STORAGESUBTYPE="bram" STORAGESIZE="64 0 1"/>
	<BindNode BINDTYPE="interface" DISPLAY="bind_storage bram" ID="" IMPL="" LATENCY="" OPTYPE="" PRAGMA="no" RTLNAME="" SOURCE="" VARIABLE="c1_conv_layer_map_db" MODULE="conv_fprop1" LOOP="" BUNDLEDNAME="" DSP="0" BRAM="0" URAM="0" USAGE="interface" STORAGESUBTYPE="bram" STORAGESIZE="64 0 1"/>
	<BindNode BINDTYPE="interface" DISPLAY="bind_storage bram" ID="" IMPL="" LATENCY="" OPTYPE="" PRAGMA="no" RTLNAME="" SOURCE="" VARIABLE="c1_conv_layer_kernel" MODULE="conv_fprop1" LOOP="" BUNDLEDNAME="" DSP="0" BRAM="0" URAM="0" USAGE="interface" STORAGESUBTYPE="bram" STORAGESIZE="3200 0 1"/>
	<BindNode BINDTYPE="interface" DISPLAY="bind_storage bram" ID="" IMPL="" LATENCY="" OPTYPE="" PRAGMA="no" RTLNAME="" SOURCE="" VARIABLE="c1_conv_layer_map_common" MODULE="conv_fprop1" LOOP="" BUNDLEDNAME="" DSP="0" BRAM="0" URAM="0" USAGE="interface" STORAGESUBTYPE="bram" STORAGESIZE="64 0 1"/>
	<BindNode BINDTYPE="interface" DISPLAY="bind_storage bram" ID="" IMPL="" LATENCY="" OPTYPE="" PRAGMA="no" RTLNAME="" SOURCE="" VARIABLE="pconnection" MODULE="conv_fprop1" LOOP="" BUNDLEDNAME="" DSP="0" BRAM="0" URAM="0" USAGE="interface" STORAGESUBTYPE="bram" STORAGESIZE="1 0 1"/>
</BindInfo>
